napari_workshop_plugin/__init__.py
napari_workshop_plugin/_reader.py
napari_workshop_plugin/_sample_data.py
napari_workshop_plugin/_version.py
napari_workshop_plugin/_widget.py
napari_workshop_plugin/napari.yaml
napari_workshop_plugin/_tests/__init__.py
napari_workshop_plugin/_tests/test_blur_and_gray.py
napari_workshop_plugin/_tests/test_display_layer.py
napari_workshop_plugin/_tests/test_initial_segment.py
napari_workshop_plugin/_tests/test_reader.py
napari_workshop_plugin/_tests/test_smooth_labels.py
napari_workshop_plugin/data/sample.npy
napari_workshop_plugin-1.0.4.dist-info/LICENSE
napari_workshop_plugin-1.0.4.dist-info/METADATA
napari_workshop_plugin-1.0.4.dist-info/WHEEL
napari_workshop_plugin-1.0.4.dist-info/entry_points.txt
napari_workshop_plugin-1.0.4.dist-info/top_level.txt
napari_workshop_plugin-1.0.4.dist-info/RECORD
