Metadata-Version: 2.1
Name: napari-workshop-plugin
Version: 1.0.4
Summary: A plugin to demonstrate some concepts from the 2023 workshop on software development related to napari
Home-page: https://www.napari-hub.org/plugins/napari-workshop-plugin
Author: MetaCell
Author-email: sean.martin@metacell.us
License: MIT
Project-URL: Bug Tracker, https://github.com/seankmartin/napari-software-development-workshop/issues
Project-URL: Documentation, https://seankmartin.github.io/napari-software-development-workshop/
Project-URL: Source Code, https://github.com/seankmartin/napari-software-development-workshop
Project-URL: User Support, https://napari.zulipchat.com
Classifier: Development Status :: 2 - Pre-Alpha
Classifier: Framework :: napari
Classifier: Intended Audience :: Developers
Classifier: License :: OSI Approved :: MIT License
Classifier: Operating System :: OS Independent
Classifier: Programming Language :: Python
Classifier: Programming Language :: Python :: 3
Classifier: Programming Language :: Python :: 3 :: Only
Classifier: Programming Language :: Python :: 3.8
Classifier: Programming Language :: Python :: 3.9
Classifier: Programming Language :: Python :: 3.10
Classifier: Programming Language :: Python :: 3.11
Classifier: Topic :: Scientific/Engineering :: Image Processing
Requires-Python: >=3.8
License-File: LICENSE
Requires-Dist: numpy <2,>=1.23
Requires-Dist: magicgui
Requires-Dist: qtpy
Provides-Extra: docs
Requires-Dist: mkdocs-material ; extra == 'docs'
Requires-Dist: mkdocstrings-python ; extra == 'docs'
Requires-Dist: mkdocstrings ; extra == 'docs'
Provides-Extra: testing
Requires-Dist: tox ; extra == 'testing'
Requires-Dist: pytest ; extra == 'testing'
Requires-Dist: pytest-cov ; extra == 'testing'
Requires-Dist: pytest-qt ; extra == 'testing'
Requires-Dist: napari ; extra == 'testing'
Requires-Dist: pyqt5 ; extra == 'testing'
